jaraco/email/__init__.py
jaraco/email/messages.py
jaraco/email/notification.py
jaraco/email/smtp.py
jaraco.email-3.1.1.dist-info/LICENSE
jaraco.email-3.1.1.dist-info/METADATA
jaraco.email-3.1.1.dist-info/WHEEL
jaraco.email-3.1.1.dist-info/top_level.txt
jaraco.email-3.1.1.dist-info/RECORD
